titanium_rhythm/__init__.py
titanium_rhythm/annotate.py
titanium_rhythm/identify.py
titanium_rhythm/modify.py
titanium_rhythm/setup_api.py
titanium_rhythm/utils.py
titanium_rhythm/info/info.json
titanium_rhythm/song_info/unknown.xml
titanium_rhythm-1.0.3.dist-info/METADATA
titanium_rhythm-1.0.3.dist-info/RECORD
titanium_rhythm-1.0.3.dist-info/WHEEL
titanium_rhythm-1.0.3.dist-info/top_level.txt
