Metadata-Version: 2.1
Name: titanium-rhythm
Version: 1.0.3
Summary: Automatic id3 modifier .mp3 files
Home-page: https://github.com/ganesh-k13/titanium-rhythm
Author: Ganesh Kathiresan
Author-email: ganesh3597@gmail.com
License: UNKNOWN
Platform: UNKNOWN
Classifier: Programming Language :: Python :: 3
Classifier: License :: OSI Approved :: MIT License
Classifier: Operating System :: OS Independent
Requires-Dist: discogs-client (==2.2.1)
Requires-Dist: eyeD3 (==0.8.7)
Requires-Dist: pyacoustid (==1.1.5)
Requires-Dist: pytest (==3.6.1)
Requires-Dist: requests (==2.18.4)
Requires-Dist: setuptools (==38.6.0)
Requires-Dist: validators (==0.12.2)
